google_meter.py
powermeter.py
rfc3339.py
setup.py
units.py
powermeter.egg-info/PKG-INFO
powermeter.egg-info/SOURCES.txt
powermeter.egg-info/dependency_links.txt
powermeter.egg-info/entry_points.txt
powermeter.egg-info/requires.txt
powermeter.egg-info/top_level.txt