Metadata-Version: 1.0
Name: powermeter
Version: 0.2.2
Summary: Google powermeter teleinfo daemon
Home-page: UNKNOWN
Author: tuxtof
Author-email: dev@geo6.net
License: GPLv2
Platform: UNKNOWN
